PypolyBest/__init__.py
bestPR/__init__.py
PypolyBest-0.6.11.dist-info/LICENSE.txt
PypolyBest-0.6.11.dist-info/METADATA
PypolyBest-0.6.11.dist-info/WHEEL
PypolyBest-0.6.11.dist-info/top_level.txt
PypolyBest-0.6.11.dist-info/RECORD
