Metadata-Version: 2.1
Name: PypolyBest
Version: 0.6.11
Summary: see long description
Home-page: UNKNOWN
Author: Ujjawal
Author-email: ujjawald21@iitk.ac.in
License: UNKNOWN
Platform: UNKNOWN
Classifier: Programming Language :: Python :: 3.8
Classifier: Operating System :: OS Independent
Requires-Dist: scikit-learn
